__init__.py
csv_wizard.py
RowFilter.py
csv_wizard-1.1.0.post4.dist-info/WHEEL
csv_wizard-1.1.0.post4.dist-info/METADATA
csv_wizard-1.1.0.post4.dist-info/licenses/LICENSE
csv_wizard-1.1.0.post4.dist-info/RECORD
