Metadata-Version: 2.1
Name: csv_wizard
Version: 1.1.0.post4
Summary: Handy extension to Python csv standard library package
License: MIT
Author-email: liquidsnake <bentsoft365@gmail.com>
Requires-Python: >=3.9
Requires-Dist: chardet>=5.1.0
